{
  "pokemon_id": 876,
  "forms": [
    {
      "id": "male",
      "order": 0,
      "name": {
        "ja": "イエッサン",
        "en": "Indeedee"
      },
      "form_type": "normal",
      "region": "galar",
      "types": [
        "psychic",
        "normal"
      ],
      "stats": {
        "hp": 60,
        "attack": 65,
        "defense": 55,
        "sp_attack": 105,
        "sp_defense": 95,
        "speed": 95
      },
      "ability_ids": [
        39,
        28
      ],
      "hidden_ability_id": 227
    },
    {
      "id": "female",
      "order": 1,
      "name": {
        "ja": "メスのすがた",
        "en": "Female"
      },
      "form_type": "normal",
      "region": "galar",
      "types": [
        "psychic",
        "normal"
      ],
      "stats": {
        "hp": 70,
        "attack": 55,
        "defense": 65,
        "sp_attack": 95,
        "sp_defense": 105,
        "speed": 85
      },
      "ability_ids": [
        20,
        28
      ],
      "hidden_ability_id": 227
    }
  ]
}
